[
    {
        "created": "20230423092036689",
        "tags": "[[第一推动丛书·综合系列/num_16/第2章 动力学、混沌和预测]] ? .",
        "modified": "20230423092036689",
        "title": "第一推动丛书·综合系列/num_16/第2章 动力学、混沌和预测/摘录句子",
        "type": "text/vnd.tiddlywiki",
        "text": "",
        "caption": "再一次一无所知[14]，从头开始……这让我很开心。\n                    \n                \n                    \n                        对于我们来说平常大小的事物，人们为之写诗的那些——云彩、水仙花、瀑布，它们对于我们，就好像天堂对于古希腊人，充满了神奇……现在也许是最好的时代，你曾以为正确的东西几乎都是错的。\n                    \n                \n                    \n                        ——斯托帕德（Tom Stoppard），\n                    \n                \n                    \n                        《阿卡狄亚》（Arcadia）",
        "priority": "0",
        "interval": "2",
        "due": "20230425092036689",
        "review": "20230423092036689",
        "annotate-text": "再一次一无所知[14]，从头开始……这让我很开心。\n                    \n                \n                    \n                        对于我们来说平常大小的事物，人们为之写诗的那些——云彩、水仙花、瀑布，它们对于我们，就好像天堂对于古希腊人，充满了神奇……现在也许是最好的时代，你曾以为正确的东西几乎都是错的。\n                    \n                \n                    \n                        ——斯托帕德（Tom Stoppard），\n                    \n                \n                    \n                        《阿卡狄亚》（Arcadia）",
        "annotate-prefix": "    \n                    \n                        ",
        "annotate-suffix": "\n                    \n                \n           ",
        "annotate-colour": "LightSkyBlue",
        "annotate-blend-mode": "multiply",
        "tmap.id": "1733baf7-c701-48ab-beda-71739617a558"
    }
]